Workbook
Name Slicer_Brand: #N/A
Name Slicer_City: #N/A
Name Slicer_Product_Name: #N/A
Name Slicer_Sub_Category: #N/A

Sheet deshboard
A2: PRODUCT VS SALES
A3: Row Labels | B3: Sum of Sales
A4: Chair | B4: 2495925
A5: Headphones | B5: 2171575
A6: Keyboard | B6: 832050
A7: Laptop | B7: 27164500
A8: Mouse | B8: 427640
A9: Grand Total | B9: 33091690
A11: CITY VS SALES
A12: Row Labels | B12: Sum of Sales
A13: Ahmedabad | B13: 7491755
A14: Bengaluru | B14: 8818200
A15: Delhi | B15: 9930040
A16: Mumbai | B16: 6851695
A17: Grand Total | B17: 33091690
A19: BRAND VS QUANTITY
A20: Row Labels | B20: Sum of Quantity
A21: HP | B21: 602
A22: Logitech | B22: 583
A23: Nilkamal | B23: 604
A24: Dell | B24: 541
A25: Sony | B25: 675
A26: Grand Total | B26: 3005
A28: SUB CATEGORY VS SALES
A29: Row Labels | B29: Sum of Sales
A30: Accessories | B30: 1259690
A31: Audio | B31: 2171575
A32: Computers | B32: 27164500
A33: Office | B33: 2495925
A34: Grand Total | B34: 33091690

Sheet Sheet2
A1: Sales | B1: Product Name | F1: Category | H1: Order ID | I1: subcategory | J1: brand | K1: product name
A2: 1600 | B2: Mouse | C2: sum of sales | D2: =SUM(A:A) -> 33091690 | F2: Electronics | H2: ORD00001 | I2: =VLOOKUP(H2,Table1[#All],8,FALSE) -> Accessories | J2: {=_xlfn.XLOOKUP(H2,Table1[[#All],[Order ID]],Table1[[#All],[Brand]],0)} -> Logitech | K2: =INDEX(Table1[[#All],[Product Name]],MATCH(Sheet2!H2,Table1[[#All],[Order ID]],0)) -> Mouse | O2: 10,000>values | P2: category | Q2: =INDEX(Table1[[#All],[Sub Category]],2) -> Accessories
A3: 22500 | B3: Chair | C3: sale of electronics | D3: =SUMIF(F:F,"electronics",A:A) -> 30595765 | F3: Furniture | H3: ORD00002 | I3: =VLOOKUP(H3,Table1[#All],8,FALSE) -> Office | J3: {=_xlfn.XLOOKUP(H3,Table1[[#All],[Order ID]],Table1[[#All],[Brand]],0)} -> Nilkamal | K3: =INDEX(Table1[[#All],[Product Name]],MATCH(Sheet2!H3,Table1[[#All],[Order ID]],0)) -> Chair | O3: {=_xlfn.UNIQUE(_xlfn._xlws.FILTER(Table1[Sales],Table1[Sales]>10000))} -> 22500 | P3: {=_xlfn.UNIQUE(F2:F1001)} -> Electronics
A4: 247500 | B4: Laptop | C4: sale of mouse in eletronics | D4: =SUMIFS(A:A,B:B,"Mouse",F:F,"electronics") -> 427640 | F4: Electronics | H4: ORD00003 | I4: =VLOOKUP(H4,Table1[#All],8,FALSE) -> Computers | J4: {=_xlfn.XLOOKUP(H4,Table1[[#All],[Order ID]],Table1[[#All],[Brand]],0)} -> Dell | K4: =INDEX(Table1[[#All],[Product Name]],MATCH(Sheet2!H4,Table1[[#All],[Order ID]],0)) -> Laptop | O4: 247500 | P4: Furniture
A5: 9000 | B5: Chair | F5: Furniture | H5: ORD00004 | I5: =VLOOKUP(H5,Table1[#All],8,FALSE) -> Office | J5: {=_xlfn.XLOOKUP(H5,Table1[[#All],[Order ID]],Table1[[#All],[Brand]],0)} -> Nilkamal | K5: =INDEX(Table1[[#All],[Product Name]],MATCH(Sheet2!H5,Table1[[#All],[Order ID]],0)) -> Chair | O5: 140250
A6: 140250 | B6: Laptop | C6: total quantity | D6: =COUNT(Amazon_Sales_Data!J:J) -> 1000 | F6: Electronics | H6: ORD00005 | I6: =VLOOKUP(H6,Table1[#All],8,FALSE) -> Computers | J6: {=_xlfn.XLOOKUP(H6,Table1[[#All],[Order ID]],Table1[[#All],[Brand]],0)} -> Dell | K6: =INDEX(Table1[[#All],[Product Name]],MATCH(Sheet2!H6,Table1[[#All],[Order ID]],0)) -> Laptop | O6: 17500
A7: 5400 | B7: Keyboard | C7: quntity of mouse | D7: =COUNTIF(Table1[[#All],[Product Name]],"mouse") -> 201 | F7: Electronics | H7: ORD00006 | I7: =VLOOKUP(H7,Table1[#All],8,FALSE) -> Accessories | J7: {=_xlfn.XLOOKUP(H7,Table1[[#All],[Order ID]],Table1[[#All],[Brand]],0)} -> HP | K7: =INDEX(Table1[[#All],[Product Name]],MATCH(Sheet2!H7,Table1[[#All],[Order ID]],0)) -> Keyboard | O7: 14000
A8: 17500 | B8: Headphones | C8: quntity of laptops that are electrics | D8: =COUNTIFS(Table1[[#All],[Category]],"electronics",Table1[[#All],[Product Name]],"laptop") -> 187 | F8: Electronics | H8: ORD00007 | I8: =VLOOKUP(H8,Table1[#All],8,FALSE) -> Audio | J8: {=_xlfn.XLOOKUP(H8,Table1[[#All],[Order ID]],Table1[[#All],[Brand]],0)} -> Sony | K8: =INDEX(Table1[[#All],[Product Name]],MATCH(Sheet2!H8,Table1[[#All],[Order ID]],0)) -> Headphones | O8: 93500
A9: 14000 | B9: Headphones | F9: Electronics | H9: ORD00008 | I9: =VLOOKUP(H9,Table1[#All],8,FALSE) -> Audio | J9: {=_xlfn.XLOOKUP(H9,Table1[[#All],[Order ID]],Table1[[#All],[Brand]],0)} -> Sony | K9: =INDEX(Table1[[#All],[Product Name]],MATCH(Sheet2!H9,Table1[[#All],[Order ID]],0)) -> Headphones | O9: 14875
A10: 5950 | B10: Headphones | F10: Electronics | H10: ORD00009 | I10: =VLOOKUP(H10,Table1[#All],8,FALSE) -> Audio | J10: {=_xlfn.XLOOKUP(H10,Table1[[#All],[Order ID]],Table1[[#All],[Brand]],0)} -> Sony | K10: =INDEX(Table1[[#All],[Product Name]],MATCH(Sheet2!H10,Table1[[#All],[Order ID]],0)) -> Headphones | O10: 148500
A11: 8100 | B11: Chair | F11: Furniture | H11: ORD00010 | I11: =VLOOKUP(H11,Table1[#All],8,FALSE) -> Office | J11: {=_xlfn.XLOOKUP(H11,Table1[[#All],[Order ID]],Table1[[#All],[Brand]],0)} -> Nilkamal | K11: =INDEX(Table1[[#All],[Product Name]],MATCH(Sheet2!H11,Table1[[#All],[Order ID]],0)) -> Chair | O11: 198000
A12: 6750 | B12: Keyboard | F12: Electronics | H12: ORD00011 | I12: =VLOOKUP(H12,Table1[#All],8,FALSE) -> Accessories | J12: {=_xlfn.XLOOKUP(H12,Table1[[#All],[Order ID]],Table1[[#All],[Brand]],0)} -> HP | K12: =INDEX(Table1[[#All],[Product Name]],MATCH(Sheet2!H12,Table1[[#All],[Order ID]],0)) -> Keyboard | O12: 52250
A13: 3600 | B13: Mouse | F13: Electronics | H13: ORD00012 | I13: =VLOOKUP(H13,Table1[#All],8,FALSE) -> Accessories | J13: {=_xlfn.XLOOKUP(H13,Table1[[#All],[Order ID]],Table1[[#All],[Brand]],0)} -> Logitech | K13: =INDEX(Table1[[#All],[Product Name]],MATCH(Sheet2!H13,Table1[[#All],[Order ID]],0)) -> Mouse | O13: 12150
A14: 7650 | B14: Chair | F14: Furniture | H14: ORD00013 | I14: =VLOOKUP(H14,Table1[#All],8,FALSE) -> Office | J14: {=_xlfn.XLOOKUP(H14,Table1[[#All],[Order ID]],Table1[[#All],[Brand]],0)} -> Nilkamal | K14: =INDEX(Table1[[#All],[Product Name]],MATCH(Sheet2!H14,Table1[[#All],[Order ID]],0)) -> Chair | O14: 10500
A15: 2850 | B15: Keyboard | F15: Electronics | H15: ORD00014 | I15: =VLOOKUP(H15,Table1[#All],8,FALSE) -> Accessories | J15: {=_xlfn.XLOOKUP(H15,Table1[[#All],[Order ID]],Table1[[#All],[Brand]],0)} -> HP | K15: =INDEX(Table1[[#All],[Product Name]],MATCH(Sheet2!H15,Table1[[#All],[Order ID]],0)) -> Keyboard | O15: 165000
A16: 5400 | B16: Keyboard | F16: Electronics | H16: ORD00015 | I16: =VLOOKUP(H16,Table1[#All],8,FALSE) -> Accessories | J16: {=_xlfn.XLOOKUP(H16,Table1[[#All],[Order ID]],Table1[[#All],[Brand]],0)} -> HP | K16: =INDEX(Table1[[#All],[Product Name]],MATCH(Sheet2!H16,Table1[[#All],[Order ID]],0)) -> Keyboard | O16: 16200
A17: 93500 | B17: Laptop | F17: Electronics | H17: ORD00016 | I17: =VLOOKUP(H17,Table1[#All],8,FALSE) -> Computers | J17: {=_xlfn.XLOOKUP(H17,Table1[[#All],[Order ID]],Table1[[#All],[Brand]],0)} -> Dell | K17: =INDEX(Table1[[#All],[Product Name]],MATCH(Sheet2!H17,Table1[[#All],[Order ID]],0)) -> Laptop | O17: 15750
A18: 14875 | B18: Headphones | F18: Electronics | H18: ORD00017 | I18: =VLOOKUP(H18,Table1[#All],8,FALSE) -> Audio | J18: {=_xlfn.XLOOKUP(H18,Table1[[#All],[Order ID]],Table1[[#All],[Brand]],0)} -> Sony | K18: =INDEX(Table1[[#All],[Product Name]],MATCH(Sheet2!H18,Table1[[#All],[Order ID]],0)) -> Headphones | O18: 19125
A19: 148500 | B19: Laptop | F19: Electronics | H19: ORD00018 | I19: =VLOOKUP(H19,Table1[#All],8,FALSE) -> Computers | J19: {=_xlfn.XLOOKUP(H19,Table1[[#All],[Order ID]],Table1[[#All],[Brand]],0)} -> Dell | K19: =INDEX(Table1[[#All],[Product Name]],MATCH(Sheet2!H19,Table1[[#All],[Order ID]],0)) -> Laptop | O19: 156750
A20: 198000 | B20: Laptop | F20: Electronics | H20: ORD00019 | I20: =VLOOKUP(H20,Table1[#All],8,FALSE) -> Computers | J20: {=_xlfn.XLOOKUP(H20,Table1[[#All],[Order ID]],Table1[[#All],[Brand]],0)} -> Dell | K20: =INDEX(Table1[[#All],[Product Name]],MATCH(Sheet2!H20,Table1[[#All],[Order ID]],0)) -> Laptop | O20: 11900
... A43: 15750 | B43: Headphones | F43: Electronics | H43: ORD00042 | I43: =VLOOKUP(H43,Table1[#All],8,FALSE) -> Audio | J43: {=_xlfn.XLOOKUP(H43,Table1[[#All],[Order ID]],Table1[[#All],[Brand]],0)} -> Sony | K43: =INDEX(Table1[[#All],[Product Name]],MATCH(Sheet2!H43,Table1[[#All],[Order ID]],0)) -> Headphones | O43: 13500
A44: 4275 | B44: Keyboard | F44: Electronics | H44: ORD00043 | I44: =VLOOKUP(H44,Table1[#All],8,FALSE) -> Accessories | J44: {=_xlfn.XLOOKUP(H44,Table1[[#All],[Order ID]],Table1[[#All],[Brand]],0)} -> HP | K44: =INDEX(Table1[[#All],[Product Name]],MATCH(Sheet2!H44,Table1[[#All],[Order ID]],0)) -> Keyboard
A45: 10500 | B45: Headphones | F45: Electronics | H45: ORD00044 | I45: =VLOOKUP(H45,Table1[#All],8,FALSE) -> Audio | J45: {=_xlfn.XLOOKUP(H45,Table1[[#All],[Order ID]],Table1[[#All],[Brand]],0)} -> Sony | K45: =INDEX(Table1[[#All],[Product Name]],MATCH(Sheet2!H45,Table1[[#All],[Order ID]],0)) -> Headphones
A46: 2880 | B46: Mouse | F46: Electronics | H46: ORD00045 | I46: =VLOOKUP(H46,Table1[#All],8,FALSE) -> Accessories | J46: {=_xlfn.XLOOKUP(H46,Table1[[#All],[Order ID]],Table1[[#All],[Brand]],0)} -> Logitech | K46: =INDEX(Table1[[#All],[Product Name]],MATCH(Sheet2!H46,Table1[[#All],[Order ID]],0)) -> Mouse
A47: 1440 | B47: Mouse | F47: Electronics | H47: ORD00046 | I47: =VLOOKUP(H47,Table1[#All],8,FALSE) -> Accessories | J47: {=_xlfn.XLOOKUP(H47,Table1[[#All],[Order ID]],Table1[[#All],[Brand]],0)} -> Logitech | K47: =INDEX(Table1[[#All],[Product Name]],MATCH(Sheet2!H47,Table1[[#All],[Order ID]],0)) -> Mouse
A48: 19125 | B48: Chair | F48: Furniture | H48: ORD00047 | I48: =VLOOKUP(H48,Table1[#All],8,FALSE) -> Office | J48: {=_xlfn.XLOOKUP(H48,Table1[[#All],[Order ID]],Table1[[#All],[Brand]],0)} -> Nilkamal | K48: =INDEX(Table1[[#All],[Product Name]],MATCH(Sheet2!H48,Table1[[#All],[Order ID]],0)) -> Chair
A49: 3000 | B49: Keyboard | F49: Electronics | H49: ORD00048 | I49: =VLOOKUP(H49,Table1[#All],8,FALSE) -> Accessories | J49: {=_xlfn.XLOOKUP(H49,Table1[[#All],[Order ID]],Table1[[#All],[Brand]],0)} -> HP | K49: =INDEX(Table1[[#All],[Product Name]],MATCH(Sheet2!H49,Table1[[#All],[Order ID]],0)) -> Keyboard
A50: 156750 | B50: Laptop | F50: Electronics | H50: ORD00049 | I50: =VLOOKUP(H50,Table1[#All],8,FALSE) -> Computers | J50: {=_xlfn.XLOOKUP(H50,Table1[[#All],[Order ID]],Table1[[#All],[Brand]],0)} -> Dell | K50: =INDEX(Table1[[#All],[Product Name]],MATCH(Sheet2!H50,Table1[[#All],[Order ID]],0)) -> Laptop
A51: 165000 | B51: Laptop | F51: Electronics | H51: ORD00050 | I51: =VLOOKUP(H51,Table1[#All],8,FALSE) -> Computers | J51: {=_xlfn.XLOOKUP(H51,Table1[[#All],[Order ID]],Table1[[#All],[Brand]],0)} -> Dell | K51: =INDEX(Table1[[#All],[Product Name]],MATCH(Sheet2!H51,Table1[[#All],[Order ID]],0)) -> Laptop
A52: 3825 | B52: Keyboard | F52: Electronics | H52: ORD00051 | I52: =VLOOKUP(H52,Table1[#All],8,FALSE) -> Accessories | J52: {=_xlfn.XLOOKUP(H52,Table1[[#All],[Order ID]],Table1[[#All],[Brand]],0)} -> HP | K52: =INDEX(Table1[[#All],[Product Name]],MATCH(Sheet2!H52,Table1[[#All],[Order ID]],0)) -> Keyboard
A53: 11900 | B53: Headphones | F53: Electronics | H53: ORD00052 | I53: =VLOOKUP(H53,Table1[#All],8,FALSE) -> Audio | J53: {=_xlfn.XLOOKUP(H53,Table1[[#All],[Order ID]],Table1[[#All],[Brand]],0)} -> Sony | K53: =INDEX(Table1[[#All],[Product Name]],MATCH(Sheet2!H53,Table1[[#All],[Order ID]],0)) -> Headphones
A54: 99000 | B54: Laptop | F54: Electronics | H54: ORD00053 | I54: =VLOOKUP(H54,Table1[#All],8,FALSE) -> Computers | J54: {=_xlfn.XLOOKUP(H54,Table1[[#All],[Order ID]],Table1[[#All],[Brand]],0)} -> Dell | K54: =INDEX(Table1[[#All],[Product Name]],MATCH(Sheet2!H54,Table1[[#All],[Order ID]],0)) -> Laptop
A55: 198000 | B55: Laptop | F55: Electronics | H55: ORD00054 | I55: =VLOOKUP(H55,Table1[#All],8,FALSE) -> Computers | J55: {=_xlfn.XLOOKUP(H55,Table1[[#All],[Order ID]],Table1[[#All],[Brand]],0)} -> Dell | K55: =INDEX(Table1[[#All],[Product Name]],MATCH(Sheet2!H55,Table1[[#All],[Order ID]],0)) -> Laptop
... A1001: 6000 | B1001: Keyboard | F1001: Electronics | H1001: ORD01000 | I1001: =VLOOKUP(H1001,Table1[#All],8,FALSE) -> Accessories | J1001: {=_xlfn.XLOOKUP(H1001,Table1[[#All],[Order ID]],Table1[[#All],[Brand]],0)} -> HP | K1001: =INDEX(Table1[[#All],[Product Name]],MATCH(Sheet2!H1001,Table1[[#All],[Order ID]],0)) -> Keyboard

Sheet Amazon_Sales_Data
A1: Order ID | B1: Order Date | C1: Customer ID | D1: Customer Name | E1: Product ID | F1: Product Name | G1: Category | H1: Sub Category | I1: Brand | J1: Quantity | K1: Unit Price | L1: Discount % | M1: Sales | N1: Cost | O1: Profit | P1: City | Q1: State | R1: Region | S1: Payment Mode | T1: Delivery Status | U1: Return Status | V1: Rating | W1: profit%
A2: ORD00001 | B2: 45771 | C2: C1581 | D2: Customer 305 | E2: P1002 | F2: Mouse | G2: Electronics | H2: Accessories | I2: Logitech | J2: 2 | K2: 800 | L2: 0 | M2: 1600 | N2: 1120 | O2: 480 | P2: Delhi | Q2: Delhi | R2: North | S2: Card | T2: Delivered | U2: Yes | V2: 4 | W2: =Table1[[#This Row],[Profit]]/Table1[[#This Row],[Sales]] -> 0.3
A3: ORD00002 | B3: 45955 | C3: C1734 | D3: Customer 165 | E3: P1005 | F3: Chair | G3: Furniture | H3: Office | I3: Nilkamal | J3: 5 | K3: 4500 | L3: 0 | M3: 22500 | N3: 15750 | O3: 6750 | P3: Ahmedabad | Q3: Gujarat | R3: West | S3: UPI | T3: Cancelled | U3: No | V3: 5 | W3: =Table1[[#This Row],[Profit]]/Table1[[#This Row],[Sales]] -> 0.3
A4: ORD00003 | B4: 45734 | C4: C1714 | D4: Customer 299 | E4: P1001 | F4: Laptop | G4: Electronics | H4: Computers | I4: Dell | J4: 5 | K4: 55000 | L4: 10 | M4: 247500 | N4: 192500 | O4: 55000 | P4: Delhi | Q4: Delhi | R4: North | S4: Card | T4: Pending | U4: No | V4: 5 | W4: =Table1[[#This Row],[Profit]]/Table1[[#This Row],[Sales]] -> 0.22222222
A5: ORD00004 | B5: 45753 | C5: C1315 | D5: Customer 190 | E5: P1005 | F5: Chair | G5: Furniture | H5: Office | I5: Nilkamal | J5: 2 | K5: 4500 | L5: 0 | M5: 9000 | N5: 6300 | O5: 2700 | P5: Delhi | Q5: Delhi | R5: North | S5: Cash | T5: Delivered | U5: Yes | V5: 2 | W5: =Table1[[#This Row],[Profit]]/Table1[[#This Row],[Sales]] -> 0.3
A6: ORD00005 | B6: 45978 | C6: C1397 | D6: Customer 353 | E6: P1001 | F6: Laptop | G6: Electronics | H6: Computers | I6: Dell | J6: 3 | K6: 55000 | L6: 15 | M6: 140250 | N6: 115500 | O6: 24750 | P6: Ahmedabad | Q6: Gujarat | R6: West | S6: Cash | T6: Delivered | U6: No | V6: 2 | W6: =Table1[[#This Row],[Profit]]/Table1[[#This Row],[Sales]] -> 0.17647059
A7: ORD00006 | B7: 45992 | C7: C1589 | D7: Customer 92 | E7: P1003 | F7: Keyboard | G7: Electronics | H7: Accessories | I7: HP | J7: 4 | K7: 1500 | L7: 10 | M7: 5400 | N7: 4200 | O7: 1200 | P7: Ahmedabad | Q7: Gujarat | R7: West | S7: Card | T7: Pending | U7: Yes | V7: 5 | W7: =Table1[[#This Row],[Profit]]/Table1[[#This Row],[Sales]] -> 0.22222222
A8: ORD00007 | B8: 45914 | C8: C1584 | D8: Customer 91 | E8: P1004 | F8: Headphones | G8: Electronics | H8: Audio | I8: Sony | J8: 5 | K8: 3500 | L8: 0 | M8: 17500 | N8: 12250 | O8: 5250 | P8: Delhi | Q8: Delhi | R8: North | S8: UPI | T8: Cancelled | U8: Yes | V8: 4 | W8: =Table1[[#This Row],[Profit]]/Table1[[#This Row],[Sales]] -> 0.3
A9: ORD00008 | B9: 45779 | C9: C1050 | D9: Customer 169 | E9: P1004 | F9: Headphones | G9: Electronics | H9: Audio | I9: Sony | J9: 4 | K9: 3500 | L9: 0 | M9: 14000 | N9: 9800 | O9: 4200 | P9: Ahmedabad | Q9: Gujarat | R9: West | S9: Card | T9: Delivered | U9: Yes | V9: 3 | W9: =Table1[[#This Row],[Profit]]/Table1[[#This Row],[Sales]] -> 0.3
A10: ORD00009 | B10: 45875 | C10: C1766 | D10: Customer 349 | E10: P1004 | F10: Headphones | G10: Electronics | H10: Audio | I10: Sony | J10: 2 | K10: 3500 | L10: 15 | M10: 5950 | N10: 4900 | O10: 1050 | P10: Delhi | Q10: Delhi | R10: North | S10: Card | T10: Delivered | U10: No | V10: 3 | W10: =Table1[[#This Row],[Profit]]/Table1[[#This Row],[Sales]] -> 0.17647059
A11: ORD00010 | B11: 45934 | C11: C1832 | D11: Customer 168 | E11: P1005 | F11: Chair | G11: Furniture | H11: Office | I11: Nilkamal | J11: 2 | K11: 4500 | L11: 10 | M11: 8100 | N11: 6300 | O11: 1800 | P11: Ahmedabad | Q11: Gujarat | R11: West | S11: Card | T11: Delivered | U11: No | V11: 5 | W11: =Table1[[#This Row],[Profit]]/Table1[[#This Row],[Sales]] -> 0.22222222
A12: ORD00011 | B12: 45838 | C12: C1369 | D12: Customer 155 | E12: P1003 | F12: Keyboard | G12: Electronics | H12: Accessories | I12: HP | J12: 5 | K12: 1500 | L12: 10 | M12: 6750 | N12: 5250 | O12: 1500 | P12: Delhi | Q12: Delhi | R12: North | S12: UPI | T12: Pending | U12: Yes | V12: 1 | W12: =Table1[[#This Row],[Profit]]/Table1[[#This Row],[Sales]] -> 0.22222222
A13: ORD00012 | B13: 45911 | C13: C1514 | D13: Customer 71 | E13: P1002 | F13: Mouse | G13: Electronics | H13: Accessories | I13: Logitech | J13: 5 | K13: 800 | L13: 10 | M13: 3600 | N13: 2800 | O13: 800 | P13: Ahmedabad | Q13: Gujarat | R13: West | S13: Card | T13: Pending | U13: No | V13: 1 | W13: =Table1[[#This Row],[Profit]]/Table1[[#This Row],[Sales]] -> 0.22222222
... A1001: ORD01000 | B1001: 45725 | C1001: C1173 | D1001: Customer 166 | E1001: P1003 | F1001: Keyboard | G1001: Electronics | H1001: Accessories | I1001: HP | J1001: 4 | K1001: 1500 | L1001: 0 | M1001: 6000 | N1001: 4200 | O1001: 1800 | P1001: Ahmedabad | Q1001: Gujarat | R1001: West | S1001: Card | T1001: Pending | U1001: Yes | V1001: 2 | W1001: =Table1[[#This Row],[Profit]]/Table1[[#This Row],[Sales]] -> 0.3
